dtexp/__init__.py
dtexp/addition.py
dtexp/conditions.py
dtexp/exceptions.py
dtexp/parse_expression.py
dtexp/parse_timestamp.py
dtexp/py.typed
dtexp-0.1.1.dist-info/METADATA
dtexp-0.1.1.dist-info/WHEEL
dtexp-0.1.1.dist-info/licenses/LICENSE
dtexp-0.1.1.dist-info/RECORD
