Metadata-Version: 2.4
Name: dtexp
Version: 0.1.1
Summary: A datetime expression parser
Project-URL: homepage, https://github.com/stewit/dtexp
Project-URL: documentation, https://github.com/stewit/dtexp
Project-URL: repository, https://github.com/stewit/dtexp
Author: stewit
License: MIT License
License-File: LICENSE
Classifier: License :: OSI Approved :: MIT License
Classifier: Programming Language :: Python :: 3
Classifier: Programming Language :: Python :: 3.10
Classifier: Programming Language :: Python :: 3.12
Classifier: Programming Language :: Python :: 3.13
Classifier: Programming Language :: Python :: 3.14
Requires-Python: >=3.11
Requires-Dist: pendulum
